README.rst
glreg.py
setup.cfg
setup.py
glreg.egg-info/PKG-INFO
glreg.egg-info/SOURCES.txt
glreg.egg-info/dependency_links.txt
glreg.egg-info/entry_points.txt
glreg.egg-info/top_level.txt