Metadata-Version: 1.1
Name: glreg
Version: 0.9.0a3
Summary: OpenGL XML API registry parser
Home-page: https://github.com/pyokagan/pyglreg
Author: Paul Tan
Author-email: pyokagan@gmail.com
License: MIT
Keywords: opengl
Platform: UNKNOWN
Classifier: Development Status :: 3 - Alpha
Classifier: Environment :: Console
Classifier: Intended Audience :: Developers
Classifier: License :: OSI Approved :: MIT License
Classifier: Operating System :: OS Independent
Classifier: Programming Language :: Python :: 2.7
Classifier: Programming Language :: Python :: 3.2
Classifier: Programming Language :: Python :: 3.3
Classifier: Programming Language :: Python :: 3.4
Classifier: Topic :: Software Development :: Code Generators
Classifier: Topic :: Software Development :: Libraries :: Python Modules
